{"date":"2025-09-10","files":[{"file":"0910\/IMG_20241017_032242.jpg","width":"2568","height":"1444","date":null,"thumbnail":"thumbnails\/2f949d2d-995c-44ef-9f0a-6fb2dc1afa64.jpg"},{"file":"0910\/IMG_20241017_032157.jpg","width":"1444","height":"2568","date":null,"thumbnail":"thumbnails\/af7b91c1-6c83-48b2-b3bc-e7675b24e132.jpg"},{"file":"0910\/IMG_20241017_032233.jpg","width":"1444","height":"2568","date":null,"thumbnail":"thumbnails\/d7082a5e-cc10-4f12-b614-ce6b3060433a.jpg"},{"file":"0910\/IMG_20241017_032228.jpg","width":"1444","height":"2568","date":null,"thumbnail":"thumbnails\/f79a0e70-fdfb-44d3-ba02-d401fa730258.jpg"},{"file":"0910\/IMG_20241017_032230.jpg","width":"1444","height":"2568","date":null,"thumbnail":"thumbnails\/3f32fce6-945f-44aa-b7d6-ef44379eaf48.jpg"},{"file":"0910\/IMG_20241017_032334.jpg","width":"1536","height":"2048","date":null,"thumbnail":"thumbnails\/95adad8c-493e-42b8-ac5d-33b2f4705363.jpg"},{"file":"0910\/IMG_20241017_032226.jpg","width":"1444","height":"2568","date":null,"thumbnail":"thumbnails\/3a74fe51-3b00-4a37-ab1b-38d5304661c7.jpg"},{"file":"0910\/IMG_20241017_032212.jpg","width":"1444","height":"2568","date":null,"thumbnail":"thumbnails\/36778382-5a04-4b9f-8ad0-493a1d5ca16e.jpg"},{"file":"0910\/IMG_20241017_032222.jpg","width":"1444","height":"2568","date":null,"thumbnail":"thumbnails\/41583baf-5d8e-49c9-89d4-29b035eee8e9.jpg"},{"file":"0910\/IMG_20241017_032209.jpg","width":"1444","height":"2568","date":null,"thumbnail":"thumbnails\/49c2d964-03c9-4018-9405-0108d208ebed.jpg"},{"file":"0910\/IMG_20241017_032210.jpg","width":"1444","height":"2568","date":null,"thumbnail":"thumbnails\/6eee14cd-1858-4393-8f13-43b9f1db97c0.jpg"},{"file":"0910\/IMG_20241017_032206.jpg","width":"1444","height":"2568","date":null,"thumbnail":"thumbnails\/ff7fbce8-00de-4e93-a21c-70ae60b1d0b9.jpg"},{"file":"0910\/IMG_20241017_032203.jpg","width":"1444","height":"2568","date":null,"thumbnail":"thumbnails\/e39cb8a8-dfe0-41b7-a20d-0b093b40bd83.jpg"},{"file":"0910\/IMG_20241017_032159.jpg","width":"1444","height":"2568","date":null,"thumbnail":"thumbnails\/8581915c-8db6-47e0-871f-f783e1fdbdc7.jpg"},{"file":"0910\/IMG_20241017_032244.jpg","width":"2568","height":"1444","date":null,"thumbnail":"thumbnails\/4cf3aa69-a954-4fff-8d77-9330fbcbf6ab.jpg"},{"file":"0910\/IMG_20241017_032224.jpg","width":"1444","height":"2568","date":null,"thumbnail":"thumbnails\/3cc7c64a-36a0-4ee7-8fc4-f110949c628b.jpg"},{"file":"0910\/IMG_20241017_032245.jpg","width":"2568","height":"1444","date":null,"thumbnail":"thumbnails\/d4220639-3c24-472a-b83a-94618e887df8.jpg"},{"file":"0910\/IMG_20241017_032231.jpg","width":"1444","height":"2568","date":null,"thumbnail":"thumbnails\/54e934b9-63d9-48d2-9f19-4887c9469aee.jpg"},{"file":"0910\/IMG_20241017_032135.jpg","width":"2568","height":"1444","date":null,"thumbnail":"thumbnails\/4f458907-11fa-4a37-8b47-3a5ba4ae9079.jpg"},{"file":"https:\/\/youtu.be\/li9uj1cTAXY","width":0,"height":0,"date":"2024-09-10 19:57:00","thumbnail":"https:\/\/i.ytimg.com\/vi_webp\/li9uj1cTAXY\/mqdefault.webp"},{"file":"0910\/VIDEO_DOWNLOAD_1725968405576_1729110209509.mp4","width":"720","height":"1280","date":"2024-09-10T11:55:18.000000Z","thumbnail":"thumbnails\/76a079b0-d28e-42c1-9fc1-4b892b1af910.jpg"},{"file":"0910\/VIDEO_DOWNLOAD_1725968405587_1729110212041.mp4","width":"1280","height":"720","date":"2024-09-10T11:40:06.000000Z","thumbnail":"thumbnails\/d2cbb2d7-2e9a-4561-ae36-214bea17d6c3.jpg"},{"file":"0910\/VIDEO_DOWNLOAD_1725942895202_1729110196219.mp4","width":"1280","height":"720","date":"2024-09-10T04:35:59.000000Z","thumbnail":"thumbnails\/aae85aba-5227-40e6-ba50-470d4d9382a3.jpg"},{"file":"0910\/VIDEO_DOWNLOAD_1725942895197_1729110193898.mp4","width":"1280","height":"720","date":"2024-09-10T04:35:53.000000Z","thumbnail":"thumbnails\/bde8f94b-408d-4e85-a8ba-d182f6e9c20b.jpg"},{"file":"0910\/VIDEO_DOWNLOAD_1725942895188_1729110189700.mp4","width":"720","height":"1280","date":"2024-09-10T04:35:48.000000Z","thumbnail":"thumbnails\/c5c698c8-3bfe-454e-819e-50a15ead7a03.jpg"},{"file":"0910\/VIDEO_DOWNLOAD_1725942895206_1729110198100.mp4","width":"1280","height":"720","date":"2024-09-10T04:34:57.000000Z","thumbnail":"thumbnails\/383d34cf-f08b-43fb-aa30-43c35d181da9.jpg"},{"file":"0910\/VIDEO_DOWNLOAD_1725942728583_1729110135512.mp4","width":"1280","height":"720","date":"2024-09-10T04:32:09.000000Z","thumbnail":"thumbnails\/ecfb826c-afc6-4ecb-ace9-ae5a7421a3c6.jpg"}]}