{"date":"2024-10-17","files":[{"file":"1017\/IMG_3962.JPG","width":"1920","height":"2560","date":null,"thumbnail":"thumbnails\/8c536eea-8d2d-4b98-be37-f85b6c066ecf.jpg"},{"file":"1017\/IMG_20241122_062132.jpg","width":"956","height":"1276","date":null,"thumbnail":"thumbnails\/2110566d-c6d5-4f1f-9757-672713360d13.jpg"},{"file":"1017\/IMG_3960.JPG","width":"2560","height":"1920","date":null,"thumbnail":"thumbnails\/2eee2295-02aa-4b81-a313-a674b11caf6d.jpg"},{"file":"1017\/IMG_20241122_062109.jpg","width":"2568","height":"1444","date":null,"thumbnail":"thumbnails\/14c1215a-6d9e-4fba-a5a5-4538d92e21f4.jpg"},{"file":"1017\/IMG_20241122_062121.jpg","width":"2568","height":"1444","date":null,"thumbnail":"thumbnails\/35d48edb-2a3b-4e18-ac48-cafdd2bffe70.jpg"},{"file":"1017\/IMG_3963.JPG","width":"2048","height":"1536","date":null,"thumbnail":"thumbnails\/acbe2996-8ac1-47c3-9c83-5b34803ab516.jpg"},{"file":"1017\/IMG_20241122_062105.jpg","width":"1444","height":"2568","date":null,"thumbnail":"thumbnails\/dfbc750d-e485-4d37-981c-56430c837f26.jpg"},{"file":"1017\/IMG_20241122_061904.jpg","width":"1536","height":"2048","date":null,"thumbnail":"thumbnails\/2fe32ca7-1004-4689-9613-0e9bb099a3ae.jpg"},{"file":"1017\/IMG_20241122_061906.jpg","width":"1536","height":"2048","date":null,"thumbnail":"thumbnails\/3ce32822-67b9-4a5d-8cb2-9164e05d69e2.jpg"},{"file":"1017\/IMG_20241122_061855.jpg","width":"1536","height":"2048","date":null,"thumbnail":"thumbnails\/dfef411d-9a5c-40ea-b44d-a92c44bd65e2.jpg"},{"file":"1017\/IMG_20241122_061858.jpg","width":"2048","height":"1536","date":null,"thumbnail":"thumbnails\/ce1c45cc-7e42-4918-ad21-da67485c4167.jpg"},{"file":"1017\/IMG_20241122_061840.jpg","width":"1536","height":"2048","date":null,"thumbnail":"thumbnails\/b4c3119f-a95e-4761-8dc5-1e2d54b690db.jpg"},{"file":"1017\/IMG_20241122_061839.jpg","width":"1536","height":"2048","date":null,"thumbnail":"thumbnails\/40c1375d-d09a-41c0-a607-b3b5934b0c8d.jpg"},{"file":"1017\/IMG_20241122_061836.jpg","width":"1536","height":"2048","date":null,"thumbnail":"thumbnails\/c51ced14-23d1-4696-a5e7-e3ef29348e59.jpg"},{"file":"1017\/IMG_20241122_062043.jpg","width":"1444","height":"2568","date":null,"thumbnail":"thumbnails\/278059b2-ad5b-46de-aa6e-215d03130a9c.jpg"},{"file":"1017\/IMG_20241122_062014.jpg","width":"1276","height":"956","date":null,"thumbnail":"thumbnails\/2a624429-efb5-4d87-80d5-240d8bbf2eac.jpg"},{"file":"1017\/IMG_20241122_062056.jpg","width":"2568","height":"1444","date":null,"thumbnail":"thumbnails\/3c0b19ee-509b-46cd-accb-c978385a6fd8.jpg"},{"file":"1017\/IMG_20241122_062017.jpg","width":"1276","height":"956","date":null,"thumbnail":"thumbnails\/182dd2c3-df6c-4d4d-a801-082e0cd6dbe7.jpg"},{"file":"1017\/IMG_20241122_062101.jpg","width":"1444","height":"2568","date":null,"thumbnail":"thumbnails\/ef6c2daf-4116-4ef2-9e01-35cf658d9f5f.jpg"},{"file":"1017\/IMG_20241122_062023.jpg","width":"960","height":"1280","date":null,"thumbnail":"thumbnails\/603df3e2-b642-482a-ae26-9ecee7c032e7.jpg"},{"file":"1017\/IMG_20241122_062106.jpg","width":"1444","height":"2568","date":null,"thumbnail":"thumbnails\/ba3727f7-6bf4-470a-9b28-f24d94e75a28.jpg"},{"file":"1017\/IMG_20241122_062030.jpg","width":"960","height":"1280","date":null,"thumbnail":"thumbnails\/3f1a47a8-5cc7-4e7c-b85c-4a00580465c6.jpg"},{"file":"1017\/IMG_20241122_062112.jpg","width":"2568","height":"1444","date":null,"thumbnail":"thumbnails\/1aacc32e-b910-4449-9d66-49a753f39b1a.jpg"},{"file":"1017\/IMG_20241122_062032.jpg","width":"960","height":"1280","date":null,"thumbnail":"thumbnails\/b3e01414-5c0d-4ea7-b29e-0cf23be07c87.jpg"},{"file":"1017\/IMG_20241122_062125.jpg","width":"2568","height":"1444","date":null,"thumbnail":"thumbnails\/f1a47ecd-f464-4b61-b250-5f6396251fad.jpg"},{"file":"1017\/IMG_20241122_062035.jpg","width":"1276","height":"956","date":null,"thumbnail":"thumbnails\/67de7c74-8df7-4b4f-bc00-0aebf3ba7021.jpg"},{"file":"1017\/IMG_20241122_062134.jpg","width":"956","height":"1276","date":null,"thumbnail":"thumbnails\/17737758-ddd9-4288-abc1-0a51d8900e89.jpg"},{"file":"1017\/IMG_20241122_062040.jpg","width":"1276","height":"956","date":null,"thumbnail":"thumbnails\/115b7a71-0e40-4ff3-9186-5467461c59df.jpg"},{"file":"1017\/IMG_3961.JPG","width":"2048","height":"1536","date":null,"thumbnail":"thumbnails\/3a54da2e-a04d-482b-b228-705e1db38257.jpg"},{"file":"1017\/IMG_20241122_062059.jpg","width":"1444","height":"2568","date":null,"thumbnail":"thumbnails\/7fc1d9c7-e641-4747-8ce8-35c9343fb8f6.jpg"},{"file":"1017\/VIDEO_DOWNLOAD_1729171135180_1732231107950.mp4","width":"1280","height":"720","date":"2024-10-17T13:20:03.000000Z","thumbnail":"thumbnails\/80c29265-93ab-401c-bcb8-74a9dc584936.jpg"},{"file":"1017\/20241017_201226.jpg","width":"1816","height":"4032","date":"2024:10:17 20:12:26","thumbnail":"thumbnails\/c26bff2f-8b47-4164-89dc-d7fa2e27b1e3.jpg"},{"file":"1017\/20241017_201222.jpg","width":"1816","height":"4032","date":"2024:10:17 20:12:24","thumbnail":"thumbnails\/d4908983-2325-46eb-9191-3c3e3f9d8a94.jpg"},{"file":"1017\/VIDEO_DOWNLOAD_1729145658739_1732231208744.mp4","width":"720","height":"1280","date":"2024-10-17T06:14:18.000000Z","thumbnail":"thumbnails\/218f895c-842e-42ad-895f-5aa3f5dc37dc.jpg"},{"file":"1017\/VIDEO_DOWNLOAD_1729145658735_1732231184734.mp4","width":"720","height":"1280","date":"2024-10-17T06:14:16.000000Z","thumbnail":"thumbnails\/a9d7fa73-c124-4443-bd9e-314520cbc687.jpg"},{"file":"1017\/VIDEO_DOWNLOAD_1729145554512_1732231253230.mp4","width":"1280","height":"720","date":"2024-10-17T04:34:07.000000Z","thumbnail":"thumbnails\/1dd73945-e761-449a-93d3-03aaf12ccf29.jpg"},{"file":"1017\/VIDEO_DOWNLOAD_1729129437675_1730428246356.mp4","width":"720","height":"1280","date":"2024-10-17T01:43:32.000000Z","thumbnail":"thumbnails\/45c0e1e9-6483-4a2a-b828-e116baa0b750.jpg"}]}