{"date":"2024-10-09","files":[{"file":"1009\/IMG_20241122_065856.jpg","width":"1536","height":"2048","date":null,"thumbnail":"thumbnails\/0c0d6079-438d-41b2-9623-ace5cb1f025c.jpg"},{"file":"1009\/IMG_20241122_065849.jpg","width":"2048","height":"1536","date":null,"thumbnail":"thumbnails\/3144f917-eed7-4816-a637-a7c82ddd606d.jpg"},{"file":"1009\/IMG_20241122_065850.jpg","width":"2048","height":"1536","date":null,"thumbnail":"thumbnails\/6a2c1885-617f-4d5d-a77f-b8c973da27f2.jpg"},{"file":"1009\/IMG_20241122_065819.jpg","width":"1536","height":"2048","date":null,"thumbnail":"thumbnails\/75815624-6526-4308-8908-a7fe974c0f01.jpg"},{"file":"1009\/IMG_20241122_065842.jpg","width":"1926","height":"2568","date":null,"thumbnail":"thumbnails\/daeb7a2a-2466-4443-9be2-f032dcbf17c3.jpg"},{"file":"1009\/IMG_20241122_065839.jpg","width":"2560","height":"1920","date":null,"thumbnail":"thumbnails\/4e663db5-2ed3-469f-acd7-91d4fe563660.jpg"},{"file":"1009\/IMG_20241122_065840.jpg","width":"2560","height":"1920","date":null,"thumbnail":"thumbnails\/75af2989-6599-4ec6-90dc-4a79344fbbd3.jpg"},{"file":"1009\/IMG_20241122_065833.jpg","width":"1536","height":"2048","date":null,"thumbnail":"thumbnails\/4536782d-55fd-4288-ab73-5c9ef5332698.jpg"},{"file":"1009\/IMG_20241122_065835.jpg","width":"1536","height":"2048","date":null,"thumbnail":"thumbnails\/59048433-c3a6-42a3-be65-7d11c106d88f.jpg"},{"file":"1009\/IMG_20241122_065826.jpg","width":"1536","height":"2048","date":null,"thumbnail":"thumbnails\/b77c1da2-4cf5-4585-be9e-44dbb4f88139.jpg"},{"file":"1009\/IMG_20241122_065832.jpg","width":"1536","height":"2048","date":null,"thumbnail":"thumbnails\/b2bfdc44-b434-4829-8ace-a13dc4a9b68a.jpg"},{"file":"1009\/IMG_20241122_065825.jpg","width":"1536","height":"2048","date":null,"thumbnail":"thumbnails\/45109225-1d68-410d-bf38-c2769a1f5015.jpg"},{"file":"1009\/IMG_20241122_065824.jpg","width":"1536","height":"2048","date":null,"thumbnail":"thumbnails\/af068e60-9296-4846-bbf4-d5d0e6b6f2fe.jpg"},{"file":"1009\/IMG_20241122_065822.jpg","width":"1536","height":"2048","date":null,"thumbnail":"thumbnails\/cfe095ea-ab62-4cdb-94b9-aa455ac3db23.jpg"},{"file":"1009\/IMG_20241122_065900.jpg","width":"2048","height":"1536","date":null,"thumbnail":"thumbnails\/83d42a5f-47d4-4207-8a2b-753d771f01d2.jpg"},{"file":"1009\/IMG_20241122_065841.jpg","width":"2560","height":"1920","date":null,"thumbnail":"thumbnails\/837a4815-2a21-4cd1-b9f7-8b0a9faf2832.jpg"},{"file":"1009\/IMG_20241122_065716.jpg","width":"2048","height":"1536","date":null,"thumbnail":"thumbnails\/708dc27e-9127-4522-8e8a-123973844e06.jpg"},{"file":"1009\/VIDEO_DOWNLOAD_1728453330249_1732233481047.mp4","width":"720","height":"1280","date":"2024-10-09T05:55:46.000000Z","thumbnail":"thumbnails\/a3c57b91-db51-4f6d-94db-1ea3e79f0ce7.jpg"},{"file":"1009\/VIDEO_DOWNLOAD_1728453330217_1732233485943.mp4","width":"1280","height":"720","date":"2024-10-09T05:55:27.000000Z","thumbnail":"thumbnails\/a52347c3-ed3a-4cb6-87fd-44b3f546d5bc.jpg"},{"file":"1009\/VIDEO_DOWNLOAD_1728453330206_1732233487976.mp4","width":"1280","height":"720","date":"2024-10-09T05:55:20.000000Z","thumbnail":"thumbnails\/fd528a3a-a011-4eb3-8b46-69663ff60078.jpg"},{"file":"1009\/VIDEO_DOWNLOAD_1728453330193_1732233490171.mp4","width":"1280","height":"720","date":"2024-10-09T05:55:19.000000Z","thumbnail":"thumbnails\/87cea223-2ecc-433d-a4d1-e82f53fb0b44.jpg"},{"file":"1009\/VIDEO_DOWNLOAD_1728452999915_1732233517368.mp4","width":"1280","height":"720","date":"2024-10-09T04:43:02.000000Z","thumbnail":"thumbnails\/506d9970-e8b3-4314-af31-af041e0db438.jpg"}]}